af_res_model_manager/__init__.py
af_res_model_manager/api_client.py
af_res_model_manager/configuration.py
af_res_model_manager/rest.py
af_res_model_manager/api/__init__.py
af_res_model_manager/api/arista_flow_service_api.py
af_res_model_manager/api/default_api.py
af_res_model_manager/api/id_udt_remote_iterator_api.py
af_res_model_manager/api/res_model_change_operations_api.py
af_res_model_manager/api/res_model_explorer_api.py
af_res_model_manager/api/res_remote_iterator_api.py
af_res_model_manager/models/__init__.py
af_res_model_manager/models/abort_service_exception.py
af_res_model_manager/models/abort_transaction_exception.py
af_res_model_manager/models/accessed_process_model_parameter.py
af_res_model_manager/models/activity_configuration.py
af_res_model_manager/models/af_configuration.py
af_res_model_manager/models/agent_unknown_exception.py
af_res_model_manager/models/attribute.py
af_res_model_manager/models/attribute_list.py
af_res_model_manager/models/authentication_exception.py
af_res_model_manager/models/configuration_exception.py
af_res_model_manager/models/data_consistency_exception.py
af_res_model_manager/models/data_context.py
af_res_model_manager/models/data_source_exception.py
af_res_model_manager/models/direct_template.py
af_res_model_manager/models/dummy_parent.py
af_res_model_manager/models/ebp_instance_reference.py
af_res_model_manager/models/id_udt_initial_remote_iterator_data.py
af_res_model_manager/models/id_udt_remote_iterator_data.py
af_res_model_manager/models/identified_udt_value.py
af_res_model_manager/models/ilm_exception.py
af_res_model_manager/models/ilm_exception_cause.py
af_res_model_manager/models/ilm_exception_stack_trace.py
af_res_model_manager/models/ilm_exception_suppressed.py
af_res_model_manager/models/incompatible_gui_context_exception.py
af_res_model_manager/models/inline_response400.py
af_res_model_manager/models/inline_response4001.py
af_res_model_manager/models/inline_response500.py
af_res_model_manager-2.0.3.dist-info/LICENSE
af_res_model_manager-2.0.3.dist-info/METADATA
af_res_model_manager-2.0.3.dist-info/WHEEL
af_res_model_manager-2.0.3.dist-info/top_level.txt
af_res_model_manager-2.0.3.dist-info/RECORD
