Metadata-Version: 2.1
Name: af-res-model-manager
Version: 2.0.3
Summary: AristaFlow BPM ResModelManager/ResModelManager REST Client
Home-page: UNKNOWN
Author: AristaFlow GmbH
Author-email: info@aristaflow.com
License: UNKNOWN
Keywords: Swagger,AristaFlowREST/ResModelManager
Platform: UNKNOWN
Requires-Dist: certifi
Requires-Dist: python-dateutil
Requires-Dist: six (>=1.10)
Requires-Dist: urllib3 (>=1.15)
